{"provides":{"Coro":{"file":"Coro.pm","version":"6.31"},"Coro::Socket":{"version":"6.31","file":"Coro/Socket.pm"},"Coro::EV":{"file":"EV/EV.pm","version":"6.31"},"Coro::Debug":{"version":"6.31","file":"Coro/Debug.pm"},"Coro::AIO":{"version":"6.31","file":"Coro/AIO.pm"},"Coro::LWP":{"version":"6.31","file":"Coro/LWP.pm"},"Coro::Select":{"version":"6.31","file":"Coro/Select.pm"},"Coro::RWLock":{"file":"Coro/RWLock.pm","version":"6.31"},"Coro::Util":{"version":"6.31","file":"Coro/Util.pm"},"Coro::AnyEvent":{"file":"Coro/AnyEvent.pm","version":"6.31"},"Coro::Signal":{"version":"6.31","file":"Coro/Signal.pm"},"Coro::Timer::Timeout":{"file":"Coro/Timer.pm","version":"6.31"},"Coro::SemaphoreSet":{"file":"Coro/SemaphoreSet.pm","version":"6.31"},"Coro::Handle::FH":{"version":"6.31","file":"Coro/Handle.pm"},"Coro::Event":{"file":"Event/Event.pm","version":"6.31"},"Coro::MakeMaker":{"version":"6.31","file":"Coro/MakeMaker.pm"},"Coro::BDB":{"file":"Coro/BDB.pm","version":"6.31"},"Coro::Storable":{"file":"Coro/Storable.pm","version":"6.31"},"Coro::Channel":{"file":"Coro/Channel.pm","version":"6.31"},"Coro::Specific":{"version":"6.31","file":"Coro/Specific.pm"},"Coro::LWP::Socket":{"file":"Coro/LWP.pm","version":"6.31"},"Coro::State":{"file":"Coro/State.pm","version":"6.31"},"Coro::Timer":{"file":"Coro/Timer.pm","version":"6.31"},"Coro::Semaphore":{"version":"6.31","file":"Coro/Semaphore.pm"},"Coro::Handle":{"version":"6.31","file":"Coro/Handle.pm"}},"dist":"Coro-6.31","pathname":"M/ML/MLEHMANN/Coro-6.31.tar.gz","name":"Coro","target":"Coro::AnyEvent","version":"6.31"}